<kml><MultiGeometry><Polygon><outerBoundaryIs><LinearRing><coordinates>19.570827073,41.6852732200001 19.581945165,41.6956910870001 19.5991632700001,41.779718158 19.5977091780001,41.8061090830001 19.5247540980001,41.835245082 19.47944505,41.8522181 19.4404182380001,41.8609731660001 19.416245164,41.8612450750001 19.3677732890001,41.84900012 19.3433271330001,41.9125000780001 19.3469450970001,41.9555540590001 19.3763912260001,42.0728091730001 19.399100149,42.1040911060001 19.3781911560001,42.1234641990001 19.3322180930001,42.152500118 19.2885361400001,42.1829091600001 19.519718083,42.4486091210001 19.6085360820001,42.5428450140001 19.611182249,42.5710360370001 19.6333270690001,42.603336036 19.651527199,42.623191089 19.7178451520001,42.6603450480001 19.7545821960001,42.640973129 19.764791186,42.5878731010001 19.7468091540001,42.545000169 19.769445154,42.500964165 19.7939541740001,42.484091058 19.822500254,42.4719361250001 19.9273541750001,42.51555404 20.056109093,42.5629091110001 20.071418137,42.560909189 20.1020821560001,42.533473208 20.1616632380001,42.5113181620001 20.2225002650001,42.4283270940001 20.239582249,42.360554043 20.249509104,42.3270732010001 20.355673284,42.311845127 20.38694516,42.3041641180001 20.457536207,42.273909136 20.508891122,42.230273115 20.5251360890001,42.2130540040001 20.5952731730001,42.043609137 20.6217361820001,41.9565270300001 20.6033271760001,41.934718156 20.5834002070001,41.918818021 20.5896450600001,41.8821911160001 20.568954164,41.874544976 20.533609187,41.776936037 20.517773257,41.744027008 20.53388227,41.634718106 20.466109218,41.555544995 20.4588181350001,41.520827152 20.470691269,41.499300078 20.508609155,41.4597180490001 20.5618733,41.408673096 20.5500001660001,41.373054031 20.524163285,41.350273192 20.4988541280001,41.3418000930001 20.5025002560001,41.304444968 20.519163312,41.246382184 20.5783271440001,41.162773202 20.6006090920001,41.093182116 20.6625002270001,41.089164167 20.740809164,40.909536125 20.807218144,40.900554078 20.8211091370001,40.908882169 20.837427194,40.9274271300001 20.9441633550001,40.9191642500001 20.963054153,40.9113821560001 20.9805361210001,40.8972090280001 20.983491245,40.855891107 20.98389123,40.79305399 21.0267822660001,40.7094270710001 21.0514540630001,40.6744450310001 21.0533270830001,40.6206912150001 21.0420822570001,40.564027035 20.949582256,40.469644961 20.920136127,40.4636001 20.833336155,40.4622180910001 20.791927206,40.43154502 20.7872180850001,40.394718122 20.758609141,40.311944984 20.736800267,40.3072180930001 20.714300221,40.270100176 20.721245131,40.225136127 20.6670822780001,40.0962450870001 20.6213911830001,40.085273176 20.6047182360001,40.0752732300001 20.5833361690001,40.0705449980001 20.5558270980001,40.06638221 20.4795822890001,40.065554078 20.4615732670001,40.074164137 20.450000206,40.0724911090001 20.430273229,40.0630540920001 20.3154181890001,39.991800203 20.3372181780001,39.92319114 20.3697181690001,39.891391205 20.4113182250001,39.8446449960001 20.4133272,39.8201359760001 20.4045821930001,39.8018000590001 20.378609189,39.7880540730001 20.306127184,39.8121180150001 20.294445158,39.807491204 20.29805407,39.7719450610001 20.318091177,39.7340912130001 20.220000111,39.647354105 20.1962451270001,39.6450001320001 20.1666632110001,39.650273187 20.14139127,39.656109171 20.0970090930001,39.6759731080001 20.0245822410001,39.6966641710001 20.0100270660001,39.6912001760001 19.9854181330001,39.694754103 19.9836091510001,39.7652732340001 19.9877821650001,39.8672181320001 19.9375001340001,39.93749117 19.857291188,40.043473127 19.8411092530001,40.051382124 19.825554117,40.0547181210001 19.7550001170001,40.082982234 19.730554129,40.1030540420001 19.616663343,40.1491642330001 19.503054021,40.1974911020001 19.4513911550001,40.226727012 19.4011091240001,40.280000042 19.289791246,40.4214540460001 19.31888215,40.4388910870001 19.341800118,40.431382075 19.391663222,40.387909167 19.4029181060001,40.369991172 19.406800268,40.3501361200001 19.4328731840001,40.3271911630001 19.46397323,40.337309126 19.47944505,40.354853958 19.487636181,40.4387450740001 19.4536091740001,40.5638821950001 19.417636057,40.577218139 19.3933271970001,40.580964179 19.337773284,40.6186091500001 19.3072091770001,40.6453090320001 19.3561092,40.696173103 19.405000171,40.819718165 19.4133270890001,40.866391117 19.452418106,40.883845089 19.4706182350001,40.883191133 19.521663355,40.9098539670001 19.5232632930001,40.9365910650001 19.5086092110001,40.9727732260001 19.461109134,41.0069450720001 19.436218234,41.0210642210001 19.450554138,41.060000173 19.513745139,41.2540180980001 19.510136059,41.276100054 19.498609098,41.293882094 19.4751360810001,41.309027019 19.4522181140001,41.3097180240001 19.442500135,41.406945083 19.5200002180001,41.5700000900001 19.5666632790001,41.5850001760001 19.584718233,41.605827027 19.586936085,41.6386091530001 19.570827073,41.6852732200001</coordinates></LinearRing></outerBoundaryIs></Polygon></MultiGeometry></kml>