<kml><MultiGeometry><Polygon><outerBoundaryIs><LinearRing><coordinates>103.990536252,1.38329109200004 103.997945184,1.36986412100003 103.994136279,1.35528212400004 103.984972345,1.3441642 103.959972313,1.32083602200004 103.841918235,1.25902703 103.798309204,1.25944495100003 103.646918286,1.30465392 103.640945174,1.31833603600006 103.643309206,1.33139101800003 103.671082307,1.39319112500004 103.67774525,1.40360899300003 103.684400313,1.41110912 103.699136202,1.42360905200007 103.713591297,1.42944503600006 103.804136136,1.44500000400006 103.817200338,1.44528213900003 103.829418303,1.44360911100006 103.848309269,1.43471809100004 103.879409315,1.41721801800003 103.894009249,1.40750004 103.967745187,1.38721801300005 103.990536252,1.38329109200004</coordinates></LinearRing></outerBoundaryIs></Polygon></MultiGeometry></kml>